{
  "addNewProductDB": [
    {
      "productCode": "001",
      "productName": "5",
      "productUnitPrice": "2",
      "id": 1
    },
    {
      "productCode": "002",
      "productName": "4",
      "productUnitPrice": "5",
      "id": 2
    },
    {
      "productCode": "003",
      "productName": "4",
      "productUnitPrice": "1",
      "id": 3
    },
    {
      "productCode": "004",
      "productName": "4",
      "productUnitPrice": "1",
      "id": 4
    },
    {
      "productCode": "005",
      "productName": "4",
      "productUnitPrice": "1",
      "id": 5
    },
    {
      "productCode": "006",
      "productName": "4",
      "productUnitPrice": "1",
      "id": 6
    },
    {
      "productCode": "009",
      "productName": "ბალი",
      "productUnitPrice": "5",
      "id": 7
    }
  ],
  "soldProductsDB": [
    {
      "distributorID": "001",
      "saleDate": "2022-01-03T20:00:00.000Z",
      "soldProductCode": 3,
      "soldProductName": "ლაქი",
      "soldProductQuantity": "10",
      "soldProductUnitPrice": "15",
      "soldProductTotalPrice": 150,
      "id": 1
    },
    {
      "distributorID": "001",
      "saleDate": "2022-01-03T20:00:00.000Z",
      "soldProductCode": 3,
      "soldProductName": "ლაქი",
      "soldProductQuantity": "10",
      "soldProductUnitPrice": "15",
      "soldProductTotalPrice": 150,
      "id": 2
    },
    {
      "distributorID": "45",
      "saleDate": "2022-01-03T20:00:00.000Z",
      "soldProductCode": 3,
      "soldProductName": "4",
      "soldProductQuantity": "4",
      "soldProductUnitPrice": "5",
      "soldProductTotalPrice": 20,
      "id": 3
    },
    {
      "distributorID": "45",
      "saleDate": "2022-01-03T20:00:00.000Z",
      "soldProductCode": 3,
      "soldProductName": "4",
      "soldProductQuantity": "4",
      "soldProductUnitPrice": "5",
      "soldProductTotalPrice": 20,
      "id": 4
    },
    {
      "distributorID": "21",
      "saleDate": "2022-01-03T20:00:00.000Z",
      "soldProductCode": 2,
      "soldProductName": "4",
      "soldProductQuantity": "2",
      "soldProductUnitPrice": "2",
      "soldProductTotalPrice": 4,
      "id": 5
    },
    {
      "distributorID": "21",
      "saleDate": "2022-01-03T20:00:00.000Z",
      "soldProductCode": 2,
      "soldProductName": "4",
      "soldProductQuantity": "2",
      "soldProductUnitPrice": "2",
      "soldProductTotalPrice": 4,
      "id": 6
    },
    {
      "distributorID": "21",
      "saleDate": "2022-01-03T20:00:00.000Z",
      "soldProductCode": 2,
      "soldProductName": "4",
      "soldProductQuantity": "2",
      "soldProductUnitPrice": "2",
      "soldProductTotalPrice": 4,
      "id": 7
    },
    {
      "distributorID": "21",
      "saleDate": "2022-01-03T20:00:00.000Z",
      "soldProductCode": 2,
      "soldProductName": "4",
      "soldProductQuantity": "2",
      "soldProductUnitPrice": "2",
      "soldProductTotalPrice": 4,
      "id": 8
    },
    {
      "distributorID": "21",
      "saleDate": "2022-01-03T20:00:00.000Z",
      "soldProductCode": 2,
      "soldProductName": "4",
      "soldProductQuantity": "2",
      "soldProductUnitPrice": "2",
      "soldProductTotalPrice": 4,
      "id": 9
    },
    {
      "distributorID": "21",
      "saleDate": "2022-01-03T20:00:00.000Z",
      "soldProductCode": 2,
      "soldProductName": "4",
      "soldProductQuantity": "2",
      "soldProductUnitPrice": "2",
      "soldProductTotalPrice": 4,
      "id": 10
    },
    {
      "distributorID": "21",
      "saleDate": "2022-01-03T20:00:00.000Z",
      "soldProductCode": 2,
      "soldProductName": "4",
      "soldProductQuantity": "2",
      "soldProductUnitPrice": "2",
      "soldProductTotalPrice": 4,
      "id": 11
    },
    {
      "distributorID": "21",
      "saleDate": "2022-01-03T20:00:00.000Z",
      "soldProductCode": 2,
      "soldProductName": "4",
      "soldProductQuantity": "2",
      "soldProductUnitPrice": "2",
      "soldProductTotalPrice": 4,
      "id": 12
    },
    {
      "distributorID": "21",
      "saleDate": "2022-01-03T20:00:00.000Z",
      "soldProductCode": 2,
      "soldProductName": "4",
      "soldProductQuantity": "2",
      "soldProductUnitPrice": "2",
      "soldProductTotalPrice": 4,
      "id": 13
    },
    {
      "distributorID": "21",
      "saleDate": "2022-01-03T20:00:00.000Z",
      "soldProductCode": 2,
      "soldProductName": "4",
      "soldProductQuantity": "2",
      "soldProductUnitPrice": "2",
      "soldProductTotalPrice": 4,
      "id": 14
    },
    {
      "distributorID": "21",
      "saleDate": "2022-01-03T20:00:00.000Z",
      "soldProductCode": 2,
      "soldProductName": "4",
      "soldProductQuantity": "2",
      "soldProductUnitPrice": "2",
      "soldProductTotalPrice": 4,
      "id": 15
    },
    {
      "distributorID": "21",
      "saleDate": "2022-01-03T20:00:00.000Z",
      "soldProductCode": 2,
      "soldProductName": "4",
      "soldProductQuantity": "2",
      "soldProductUnitPrice": "2",
      "soldProductTotalPrice": 4,
      "id": 16
    },
    {
      "distributorID": "21",
      "saleDate": "2022-01-03T20:00:00.000Z",
      "soldProductCode": 2,
      "soldProductName": "4",
      "soldProductQuantity": "2",
      "soldProductUnitPrice": "2",
      "soldProductTotalPrice": 4,
      "id": 17
    },
    {
      "distributorID": "21",
      "saleDate": "2022-01-03T20:00:00.000Z",
      "soldProductCode": 2,
      "soldProductName": "4",
      "soldProductQuantity": "2",
      "soldProductUnitPrice": "2",
      "soldProductTotalPrice": 4,
      "id": 18
    },
    {
      "distributorID": "21",
      "saleDate": "2022-01-03T20:00:00.000Z",
      "soldProductCode": 2,
      "soldProductName": "4",
      "soldProductQuantity": "2",
      "soldProductUnitPrice": "2",
      "soldProductTotalPrice": 4,
      "id": 19
    },
    {
      "distributorID": "21",
      "saleDate": "2022-01-03T20:00:00.000Z",
      "soldProductCode": 2,
      "soldProductName": "4",
      "soldProductQuantity": "2",
      "soldProductUnitPrice": "2",
      "soldProductTotalPrice": 4,
      "id": 20
    },
    {
      "distributorID": "21",
      "saleDate": "2022-01-03T20:00:00.000Z",
      "soldProductCode": 2,
      "soldProductName": "4",
      "soldProductQuantity": "2",
      "soldProductUnitPrice": "2",
      "soldProductTotalPrice": 4,
      "id": 21
    },
    {
      "distributorID": "21",
      "saleDate": "2022-01-03T20:00:00.000Z",
      "soldProductCode": 2,
      "soldProductName": "4",
      "soldProductQuantity": "2",
      "soldProductUnitPrice": "2",
      "soldProductTotalPrice": 4,
      "id": 22
    },
    {
      "distributorID": "21",
      "saleDate": "2022-01-03T20:00:00.000Z",
      "soldProductCode": 2,
      "soldProductName": "4",
      "soldProductQuantity": "2",
      "soldProductUnitPrice": "2",
      "soldProductTotalPrice": 4,
      "id": 23
    },
    {
      "distributorID": "21",
      "saleDate": "2022-01-03T20:00:00.000Z",
      "soldProductCode": 2,
      "soldProductName": "4",
      "soldProductQuantity": "2",
      "soldProductUnitPrice": "2",
      "soldProductTotalPrice": 4,
      "id": 24
    },
    {
      "distributorID": "21",
      "saleDate": "2022-01-03T20:00:00.000Z",
      "soldProductCode": 2,
      "soldProductName": "4",
      "soldProductQuantity": "2",
      "soldProductUnitPrice": "2",
      "soldProductTotalPrice": 4,
      "id": 25
    },
    {
      "distributorID": "21",
      "saleDate": "2022-01-03T20:00:00.000Z",
      "soldProductCode": 2,
      "soldProductName": "4",
      "soldProductQuantity": "2",
      "soldProductUnitPrice": "2",
      "soldProductTotalPrice": 4,
      "id": 26
    }
  ],
  "distributorList": [
    {
      "name": null,
      "sureName": null,
      "birthDay": null,
      "gender": "Male",
      "docType": "IDCard",
      "docSeries": null,
      "docNO": null,
      "docDateOfIssue": null,
      "docDateOfExpiry": null,
      "personalNo": null,
      "phone": null,
      "mobile": null,
      "email": null,
      "fax": null,
      "issuingAuthority": null,
      "addressType": "ActualAddress",
      "address": null,
      "protegeIds": [
        {
          "newProtegeObj": {
            "id": 4,
            "protege": []
          }
        },
        {
          "newProtegeObj": {
            "id": 5,
            "protege": []
          }
        },
        {
          "newProtegeObj": {
            "id": 6,
            "protege": []
          }
        }
      ],
      "id": 1
    },
    {
      "name": null,
      "sureName": null,
      "birthDay": null,
      "gender": "Male",
      "docType": "IDCard",
      "docSeries": null,
      "docNO": null,
      "docDateOfIssue": null,
      "docDateOfExpiry": null,
      "personalNo": null,
      "phone": null,
      "mobile": null,
      "email": null,
      "fax": null,
      "issuingAuthority": null,
      "addressType": "ActualAddress",
      "address": null,
      "protegeIds": [
        {
          "newProtegeObj": {
            "id": 7,
            "protege": []
          }
        },
        {
          "newProtegeObj": {
            "id": 8,
            "protege": []
          }
        },
        {
          "newProtegeObj": {
            "id": 9,
            "protege": []
          }
        }
      ],
      "id": 2
    },
    {
      "name": null,
      "sureName": null,
      "birthDay": null,
      "gender": "Male",
      "docType": "IDCard",
      "docSeries": null,
      "docNO": null,
      "docDateOfIssue": null,
      "docDateOfExpiry": null,
      "personalNo": null,
      "phone": null,
      "mobile": null,
      "email": null,
      "fax": null,
      "issuingAuthority": null,
      "addressType": "ActualAddress",
      "address": null,
      "protegeIds": [
        {
          "newProtegeObj": {
            "id": 10,
            "protege": []
          }
        },
        {
          "newProtegeObj": {
            "id": 11,
            "protege": []
          }
        },
        {
          "newProtegeObj": {
            "id": 12,
            "protege": []
          }
        }
      ],
      "id": 3
    },
    {
      "name": null,
      "sureName": null,
      "birthDay": null,
      "gender": "Male",
      "docType": "IDCard",
      "docSeries": null,
      "docNO": null,
      "docDateOfIssue": null,
      "docDateOfExpiry": null,
      "personalNo": null,
      "phone": null,
      "mobile": null,
      "email": null,
      "fax": null,
      "issuingAuthority": null,
      "addressType": "ActualAddress",
      "address": null,
      "protegeIds": [
        {
          "newProtegeObj": {
            "id": 13,
            "protege": []
          }
        },
        {
          "newProtegeObj": {
            "id": 14,
            "protege": []
          }
        },
        {
          "newProtegeObj": {
            "id": 15,
            "protege": []
          }
        }
      ],
      "id": 4
    },
    {
      "name": null,
      "sureName": null,
      "birthDay": null,
      "gender": "Male",
      "docType": "IDCard",
      "docSeries": null,
      "docNO": null,
      "docDateOfIssue": null,
      "docDateOfExpiry": null,
      "personalNo": null,
      "phone": null,
      "mobile": null,
      "email": null,
      "fax": null,
      "issuingAuthority": null,
      "addressType": "ActualAddress",
      "address": null,
      "protegeIds": [],
      "id": 5
    },
    {
      "name": null,
      "sureName": null,
      "birthDay": null,
      "gender": "Male",
      "docType": "IDCard",
      "docSeries": null,
      "docNO": null,
      "docDateOfIssue": null,
      "docDateOfExpiry": null,
      "personalNo": null,
      "phone": null,
      "mobile": null,
      "email": null,
      "fax": null,
      "issuingAuthority": null,
      "addressType": "ActualAddress",
      "address": null,
      "protegeIds": [],
      "id": 6
    },
    {
      "name": null,
      "sureName": null,
      "birthDay": null,
      "gender": "Male",
      "docType": "IDCard",
      "docSeries": null,
      "docNO": null,
      "docDateOfIssue": null,
      "docDateOfExpiry": null,
      "personalNo": null,
      "phone": null,
      "mobile": null,
      "email": null,
      "fax": null,
      "issuingAuthority": null,
      "addressType": "ActualAddress",
      "address": null,
      "protegeIds": [],
      "id": 7
    },
    {
      "name": null,
      "sureName": null,
      "birthDay": null,
      "gender": "Male",
      "docType": "IDCard",
      "docSeries": null,
      "docNO": null,
      "docDateOfIssue": null,
      "docDateOfExpiry": null,
      "personalNo": null,
      "phone": null,
      "mobile": null,
      "email": null,
      "fax": null,
      "issuingAuthority": null,
      "addressType": "ActualAddress",
      "address": null,
      "protegeIds": [],
      "id": 8
    },
    {
      "name": null,
      "sureName": null,
      "birthDay": null,
      "gender": "Male",
      "docType": "IDCard",
      "docSeries": null,
      "docNO": null,
      "docDateOfIssue": null,
      "docDateOfExpiry": null,
      "personalNo": null,
      "phone": null,
      "mobile": null,
      "email": null,
      "fax": null,
      "issuingAuthority": null,
      "addressType": "ActualAddress",
      "address": null,
      "protegeIds": [],
      "id": 9
    },
    {
      "name": null,
      "sureName": null,
      "birthDay": null,
      "gender": "Male",
      "docType": "IDCard",
      "docSeries": null,
      "docNO": null,
      "docDateOfIssue": null,
      "docDateOfExpiry": null,
      "personalNo": null,
      "phone": null,
      "mobile": null,
      "email": null,
      "fax": null,
      "issuingAuthority": null,
      "addressType": "ActualAddress",
      "address": null,
      "protegeIds": [],
      "id": 10
    },
    {
      "name": null,
      "sureName": null,
      "birthDay": null,
      "gender": "Male",
      "docType": "IDCard",
      "docSeries": null,
      "docNO": null,
      "docDateOfIssue": null,
      "docDateOfExpiry": null,
      "personalNo": null,
      "phone": null,
      "mobile": null,
      "email": null,
      "fax": null,
      "issuingAuthority": null,
      "addressType": "ActualAddress",
      "address": null,
      "protegeIds": [],
      "id": 11
    },
    {
      "name": null,
      "sureName": null,
      "birthDay": null,
      "gender": "Male",
      "docType": "IDCard",
      "docSeries": null,
      "docNO": null,
      "docDateOfIssue": null,
      "docDateOfExpiry": null,
      "personalNo": null,
      "phone": null,
      "mobile": null,
      "email": null,
      "fax": null,
      "issuingAuthority": null,
      "addressType": "ActualAddress",
      "address": null,
      "protegeIds": [],
      "id": 12
    },
    {
      "name": null,
      "sureName": null,
      "birthDay": null,
      "gender": "Male",
      "docType": "IDCard",
      "docSeries": null,
      "docNO": null,
      "docDateOfIssue": null,
      "docDateOfExpiry": null,
      "personalNo": null,
      "phone": null,
      "mobile": null,
      "email": null,
      "fax": null,
      "issuingAuthority": null,
      "addressType": "ActualAddress",
      "address": null,
      "protegeIds": [],
      "id": 13
    },
    {
      "name": null,
      "sureName": null,
      "birthDay": null,
      "gender": "Male",
      "docType": "IDCard",
      "docSeries": null,
      "docNO": null,
      "docDateOfIssue": null,
      "docDateOfExpiry": null,
      "personalNo": null,
      "phone": null,
      "mobile": null,
      "email": null,
      "fax": null,
      "issuingAuthority": null,
      "addressType": "ActualAddress",
      "address": null,
      "protegeIds": [],
      "id": 14
    },
    {
      "name": null,
      "sureName": null,
      "birthDay": null,
      "gender": "Male",
      "docType": "IDCard",
      "docSeries": null,
      "docNO": null,
      "docDateOfIssue": null,
      "docDateOfExpiry": null,
      "personalNo": null,
      "phone": null,
      "mobile": null,
      "email": null,
      "fax": null,
      "issuingAuthority": null,
      "addressType": "ActualAddress",
      "address": null,
      "protegeIds": [],
      "id": 15
    }
  ]
}